slack_transfer/__init__.py
slack_transfer/_base.py
slack_transfer/cli/__init__.py
slack_transfer/cli/bookmark.py
slack_transfer/cli/download.py
slack_transfer/cli/emoji.py
slack_transfer/cli/file_volume.py
slack_transfer/cli/main.py
slack_transfer/cli/token_test.py
slack_transfer/cli/upload.py
slack_transfer/client.py
slack_transfer/functions/__init__.py
slack_transfer/functions/common.py
slack_transfer/functions/download.py
slack_transfer/functions/upload.py
slack_transfer/interactive.py
slack_transfer/run.py
slack_transfer/version.py
slack_transfer-0.2.9.dist-info/entry_points.txt
slack_transfer-0.2.9.dist-info/LICENSE
slack_transfer-0.2.9.dist-info/WHEEL
slack_transfer-0.2.9.dist-info/METADATA
slack_transfer-0.2.9.dist-info/RECORD
