Metadata-Version: 2.1
Name: slack-transfer
Version: 0.2.9
Summary: 
License: MIT
Author: Masanori HIRANO
Author-email: masa.hirano.1996@gmail.com
Requires-Python: >=3.7,<3.11
Classifier: License :: OSI Approved :: MIT License
Classifier: Programming Language :: Python :: 3
Classifier: Programming Language :: Python :: 3.7
Classifier: Programming Language :: Python :: 3.8
Classifier: Programming Language :: Python :: 3.9
Classifier: Programming Language :: Python :: 3.10
Requires-Dist: markdownify (>=0.11.2,<0.12.0)
Requires-Dist: prompt-toolkit (>=3.0.30,<4.0.0)
Requires-Dist: python-dateutil (>=2.8.2,<3.0.0)
Requires-Dist: requests (>=2.28.1,<3.0.0)
Requires-Dist: slack-sdk (>=3.18.1,<4.0.0)
Requires-Dist: tqdm (>=4.64.0,<5.0.0)
